{
        "LiveId": "",
        "ReadText": true,
        "Language": "en",
        "Voice": {
                "Prefix": "yoooouuuu",
                "Sulfix": "donated",
                "PrefixMoney": "US$",
                "Money": "Dols",
                "FinalMensage": ""
        },
        "ChromaKeyColor": "#00ff00",
        "Colors": [
                "#FAEA00",
                "#FA0041",
                "#00BCFA",
                "#A301FA",
                "#00FA79",
                "#FAA400",
                "#7E37A5",
                "#00F5B6",
                "#9535A0"
        ]
}